npdict/__init__.py
npdict/sparse.py
npdict/utils.py
npdict/wrap.py
npdict-0.0.7.dist-info/licenses/LICENSE
npdict-0.0.7.dist-info/METADATA
npdict-0.0.7.dist-info/WHEEL
npdict-0.0.7.dist-info/top_level.txt
npdict-0.0.7.dist-info/RECORD
