Metadata-Version: 2.4
Name: npdict
Version: 0.0.7
Summary: A Python dictionary wrapper for numpy arrays
Author-email: Kwan Yuet Stephen Ho <stephenhky@yahoo.com.hk>
License: MIT
Project-URL: Documentation, https://npdict.readthedocs.io/
Project-URL: Repository, https://github.com/stephenhky/npdict
Project-URL: Issues, https://github.com/stephenhky/npdict/issues
Keywords: dictionary,numpy
Classifier: Topic :: Scientific/Engineering :: Mathematics
Classifier: License :: OSI Approved :: MIT License
Classifier: Topic :: Software Development :: Libraries :: Python Modules
Classifier: Topic :: Software Development :: Version Control :: Git
Classifier: Programming Language :: Python :: 3.9
Classifier: Programming Language :: Python :: 3.10
Classifier: Programming Language :: Python :: 3.11
Classifier: Programming Language :: Python :: 3.12
Classifier: Programming Language :: Python :: 3.13
Classifier: Intended Audience :: Science/Research
Classifier: Intended Audience :: Developers
Requires-Python: >=3.9
License-File: LICENSE
Requires-Dist: numpy
Requires-Dist: sparse
Requires-Dist: typing-extensions
Provides-Extra: test
Requires-Dist: pytest; extra == "test"
Dynamic: license-file
